nequix/__init__.py
nequix/calculator.py
nequix/data.py
nequix/jax_md.py
nequix/layer_norm.py
nequix/model.py
nequix/train.py
nequix/pft/data.py
nequix/pft/hessian.py
nequix/pft/train.py
nequix/torch/__init__.py
nequix/torch/layer_norm.py
nequix/torch/model.py
nequix/torch/muon.py
nequix/torch/train.py
nequix/torch/utils.py
nequix-0.3.6.dist-info/METADATA
nequix-0.3.6.dist-info/WHEEL
nequix-0.3.6.dist-info/entry_points.txt
nequix-0.3.6.dist-info/licenses/LICENSE
nequix-0.3.6.dist-info/RECORD
