Metadata-Version: 2.4
Name: nequix
Version: 0.3.6
Summary: Nequix source code
Project-URL: Homepage, https://pypi.org/project/nequix/
Project-URL: Repository, https://github.com/atomicarchitects/nequix
Author-email: Teddy Koker <teddy.koker@gmail.com>
License: MIT License
License-File: LICENSE
Requires-Python: >=3.10
Requires-Dist: ase-db-backends
Requires-Dist: ase>=3.24.0
Requires-Dist: cloudpickle>=3.1.1
Requires-Dist: e3nn-jax>=0.20.8
Requires-Dist: equinox>=0.11.11
Requires-Dist: h5py>=3.14.0
Requires-Dist: jax>=0.4.34; sys_platform == 'darwin'
Requires-Dist: jax[cuda12]>=0.4.34; sys_platform == 'linux'
Requires-Dist: jraph>=0.0.6.dev0
Requires-Dist: matscipy>=1.1.1
Requires-Dist: optax>=0.2.5
Requires-Dist: pyyaml>=6.0.2
Requires-Dist: tqdm>=4.67.1
Requires-Dist: wandb-osh>=1.2.2
Requires-Dist: wandb>=0.19.11
Provides-Extra: pft
Requires-Dist: phonopy>=2.43.1; extra == 'pft'
Provides-Extra: torch
Requires-Dist: e3nn>=0.5.8; extra == 'torch'
Requires-Dist: openequivariance==0.4.1; extra == 'torch'
Requires-Dist: setuptools; extra == 'torch'
Requires-Dist: torch-geometric>=2.6.1; extra == 'torch'
Requires-Dist: torch==2.7.0; extra == 'torch'
